zhinst/toolkit/__init__.py
zhinst/toolkit/_min_version.py
zhinst/toolkit/_version.py
zhinst/toolkit/command_table.py
zhinst/toolkit/exceptions.py
zhinst/toolkit/interface.py
zhinst/toolkit/py.typed
zhinst/toolkit/sequence.py
zhinst/toolkit/session.py
zhinst/toolkit/waveform.py
zhinst/toolkit/driver/__init__.py
zhinst/toolkit/driver/parsers.py
zhinst/toolkit/driver/devices/__init__.py
zhinst/toolkit/driver/devices/base.py
zhinst/toolkit/driver/devices/hdawg.py
zhinst/toolkit/driver/devices/pqsc.py
zhinst/toolkit/driver/devices/qhub.py
zhinst/toolkit/driver/devices/quantum_system_hub.py
zhinst/toolkit/driver/devices/shf.py
zhinst/toolkit/driver/devices/shfqa.py
zhinst/toolkit/driver/devices/shfqc.py
zhinst/toolkit/driver/devices/shfsg.py
zhinst/toolkit/driver/devices/uhfli.py
zhinst/toolkit/driver/devices/uhfqa.py
zhinst/toolkit/driver/modules/__init__.py
zhinst/toolkit/driver/modules/base_module.py
zhinst/toolkit/driver/modules/daq_module.py
zhinst/toolkit/driver/modules/data_streaming_module.py
zhinst/toolkit/driver/modules/device_settings_module.py
zhinst/toolkit/driver/modules/impedance_module.py
zhinst/toolkit/driver/modules/pid_advisor_module.py
zhinst/toolkit/driver/modules/precompensation_advisor_module.py
zhinst/toolkit/driver/modules/scope_module.py
zhinst/toolkit/driver/modules/shfqa_sweeper.py
zhinst/toolkit/driver/modules/sweeper_module.py
zhinst/toolkit/driver/nodes/__init__.py
zhinst/toolkit/driver/nodes/awg.py
zhinst/toolkit/driver/nodes/command_table_node.py
zhinst/toolkit/driver/nodes/multistate.py
zhinst/toolkit/driver/nodes/readout.py
zhinst/toolkit/driver/nodes/shfqa_scope.py
zhinst/toolkit/driver/nodes/spectroscopy.py
zhinst/toolkit/nodetree/__init__.py
zhinst/toolkit/nodetree/connection_dict.py
zhinst/toolkit/nodetree/helper.py
zhinst/toolkit/nodetree/node.py
zhinst/toolkit/nodetree/nodetree.py
zhinst/toolkit/resources/ct_schema_hdawg.json
zhinst/toolkit/resources/ct_schema_shfsg.json
zhinst/toolkit/resources/nodedoc_hf2.json
zhinst_toolkit-1.3.0.dist-info/METADATA
zhinst_toolkit-1.3.0.dist-info/WHEEL
zhinst_toolkit-1.3.0.dist-info/licenses/AUTHORS
zhinst_toolkit-1.3.0.dist-info/licenses/LICENSE
zhinst_toolkit-1.3.0.dist-info/RECORD
