Metadata-Version: 2.4
Name: zhinst-toolkit
Version: 1.3.0
Summary: Zurich Instruments Toolkit High Level API
Project-URL: homepage, https://github.com/zhinst/zhinst-toolkit
Author-email: Zurich Instrument <info@zhinst.com>
License: MIT
License-File: AUTHORS
License-File: LICENSE
Classifier: Development Status :: 5 - Production/Stable
Classifier: Intended Audience :: Developers
Classifier: Intended Audience :: Science/Research
Classifier: License :: OSI Approved :: MIT License
Classifier: Operating System :: OS Independent
Classifier: Programming Language :: Python :: 3.10
Classifier: Programming Language :: Python :: 3.11
Classifier: Programming Language :: Python :: 3.12
Classifier: Programming Language :: Python :: 3.13
Classifier: Programming Language :: Python :: 3.14
Classifier: Topic :: Scientific/Engineering
Requires-Python: >=3.10
Requires-Dist: jsonref>=0.2
Requires-Dist: jsonschema>=3.2.0
Requires-Dist: numpy>=1.13
Requires-Dist: pyelftools>=0.29
Requires-Dist: typing-extensions>=4.1.1
Requires-Dist: zhinst-core>=25.04
Requires-Dist: zhinst-utils>=0.4.0
